README.md
setup.py
cocoman/__init__.py
cocoman.egg-info/PKG-INFO
cocoman.egg-info/SOURCES.txt
cocoman.egg-info/dependency_links.txt
cocoman.egg-info/top_level.txt
cocoman/spider/__init__.py
cocoman/spider/errors.py
cocoman/spider/response.py
cocoman/utils/__init__.py
cocoman/utils/cookier.py
cocoman/utils/decor.py
cocoman/utils/dicter.py
cocoman/utils/func.py
cocoman/utils/log.py
cocoman/utils/pool.py
cocoman/utils/printer.py
cocoman/utils/proxy_api.py
cocoman/utils/times.py
cocoman/utils/ua.py