Metadata-Version: 2.1
Name: cocoman
Version: 0.6.3
Summary: Air Spider
Author: wauo
Author-email: markadc@126.com
Requires-Python: >=3.10
